README
setup.py
finance_helper/__init__.py
finance_helper/timeutils.py
finance_helper.egg-info/PKG-INFO
finance_helper.egg-info/SOURCES.txt
finance_helper.egg-info/dependency_links.txt
finance_helper.egg-info/requires.txt
finance_helper.egg-info/top_level.txt