Metadata-Version: 1.1
Name: finance-helper
Version: 0.0.0
Summary: A utility for Fiance
Home-page: https://github.com/caviler/finance_helper
Author: caviler
Author-email: caviler@gmail.com
License: BSD
Keywords: finance utility
Platform: UNKNOWN
Classifier: Development Status :: 3 - Alpha
Classifier: Programming Language :: Python :: 2.7
Classifier: Programming Language :: Python :: 3.4
Classifier: Programming Language :: Python :: 3.5
Classifier: License :: OSI Approved :: BSD License
